LICENSE
MANIFEST.in
README.md
setup.py
outlier_101703328/__init__.py
outlier_101703328/outlier_101703328.py
outlier_101703328.egg-info/PKG-INFO
outlier_101703328.egg-info/SOURCES.txt
outlier_101703328.egg-info/dependency_links.txt
outlier_101703328.egg-info/top_level.txt