Metadata-Version: 1.2
Name: outlier-101703328
Version: 0.0.1
Summary: This package is used to remove outliers in a dataset.
Home-page: https://github.com/manmeetkahlon/OUTLIER_101703328
Author: Manmeet
Author-email: manmeetkahlon2904@gmail.com
License: UNKNOWN
Platform: UNKNOWN
Classifier: Programming Language :: Python :: 3
Classifier: License :: OSI Approved :: MIT License
Classifier: Operating System :: OS Independent
Requires-Python: >=3.6
